[{
    "name": "USA-LOS",
    "address": "https://usa-los-tcping.torch.njs.app",
    "info": "Indexyz"
}, {
    "name": "China-广州-移动",
    "address": "https://guangzhou.mobile.torch.never.eu.org",
    "info": "DogeSpeed https://doge.me"
}, {
    "name": "China-重庆-腾讯云",
    "address": "https://cn-cq-tcping.torch.njs.app",
    "info": "Indexyz"
}, {
    "name": "China-江苏-Yge",
    "address": "https://ping.torch.meow.ren:12443",
    "info": "123"	
}, {
    "name": "China-多点同测",
    "address": "https://ping.regend.xyz",
    "info": "小灰 https://bio.regend.xyz"
}]
